miniproj/count_ones.v
//This program takes a top down approach to the given problem statement to find the number of 1's in a given 8 bit input.
//It involves having 2 counters for each half of the input, and then adding the 2 "counts" to get a 4 bit output.
//The carry out produced in the adder is ignored as the maximum output can only be 1000 = 8, and it would be redundant to retain context of that carry out bit.

module fourbitcounter(
    input [3:0] A,
    output [3:0] Count
);
assign Count = A[0]+A[1]+A[2]+A[3];
endmodule

module fourbitadder(
    input [3:0] A,
    input [3:0] B,
    output [3:0] Sum
);
assign Sum = A+B;
endmodule

module EightBitCounter (
    input [7:0] A,
    output [3:0] Count
);
    wire [3:0] Count1, Count2; 

    fourbitcounter C1 (.A(A[3:0]), .Count(Count1));
    fourbitcounter C2 (.A(A[7:4]), .Count(Count2));

    fourbitadder Adder (.A(Count1), .B(Count2), .Sum(Count));
endmodule

miniproj/tb_count_ones.v
`timescale 1 ns / 100 ps
`define TESTVECS 10

module tb;
    reg clk, reset;
    reg [7:0] A;            
    wire [3:0] Count;      

    EightBitCounter UUT (
        .A(A),
        .Count(Count)
    );

    reg [7:0] test_vecs[0:(`TESTVECS-1)];
    integer i;

    initial begin
        $dumpfile("counter_test.vcd");
        $dumpvars(0, tb);
    end

    initial clk = 1'b0;
    always #5 clk = ~clk;

    initial begin
    test_vecs[0] = 8'b10100111;
    test_vecs[1] = 8'b11111111;
    test_vecs[2] = 8'b00000000;
    test_vecs[3] = 8'b01101100;
    test_vecs[4] = 8'b11010001;
    test_vecs[5] = 8'b00101010;
    test_vecs[6] = 8'b10111100;
    test_vecs[7] = 8'b01011011;
    test_vecs[8] = 8'b10000111;
    test_vecs[9] = 8'b11100000;

    end

    initial begin
        A = 8'b0;
  
        for (i = 0; i < `TESTVECS; i = i + 1) begin
            #10;
            A = test_vecs[i];  
        end
        #100 $finish;
    end

    always @(A)
        $monitor("At time = %t, Input A = %b, Count = %d", $time, A, Count);
endmodule

miniproj/counter_test.vcd
$date
	Tue Nov 12 11:08:14 2024
$end
$version
	Icarus Verilog
$end
$timescale
	100ps
$end
$scope module tb $end
$var wire 4 ! Count [3:0] $end
$var reg 8 " A [7:0] $end
$var reg 1 # clk $end
$var integer 32 $ i [31:0] $end
$scope module UUT $end
$var wire 8 % A [7:0] $end
$var wire 4 & Count2 [3:0] $end
$var wire 4 ' Count1 [3:0] $end
$var wire 4 ( Count [3:0] $end
$scope module Adder $end
$var wire 4 ) Sum [3:0] $end
$var wire 4 * B [3:0] $end
$var wire 4 + A [3:0] $end
$upscope $end
$scope module C1 $end
$var wire 4 , A [3:0] $end
$var wire 4 - Count [3:0] $end
$upscope $end
$scope module C2 $end
$var wire 4 . A [3:0] $end
$var wire 4 / Count [3:0] $end
$upscope $end
$upscope $end
$upscope $end
$enddefinitions $end
$comment Show the parameter values. $end
$dumpall
$end
#0
$dumpvars
b0 /
b0 .
b0 -
b0 ,
b0 +
b0 *
b0 )
b0 (
b0 '
b0 &
b0 %
b0 $
0#
b0 "
b0 !
$end
#50
1#
#100
b11 '
b11 +
b11 -
b101 !
b101 (
b101 )
b10 &
b10 *
b10 /
b111 ,
b1010 .
0#
b1 $
b10100111 "
b10100111 %
#150
1#
#200
b100 '
b100 +
b100 -
b1000 !
b1000 (
b1000 )
b100 &
b100 *
b100 /
b1111 ,
b1111 .
0#
b10 $
b11111111 "
b11111111 %
#250
1#
#300
b0 '
b0 +
b0 -
b0 !
b0 (
b0 )
b0 &
b0 *
b0 /
b0 ,
b0 .
0#
b11 $
b0 "
b0 %
#350
1#
#400
b10 '
b10 +
b10 -
b100 !
b100 (
b100 )
b10 &
b10 *
b10 /
b1100 ,
b110 .
0#
b100 $
b1101100 "
b1101100 %
#450
1#
#500
b1 '
b1 +
b1 -
b100 !
b100 (
b100 )
b11 &
b11 *
b11 /
b1 ,
b1101 .
0#
b101 $
b11010001 "
b11010001 %
#550
1#
#600
b10 '
b10 +
b10 -
b11 !
b11 (
b11 )
b1 &
b1 *
b1 /
b1010 ,
b10 .
0#
b110 $
b101010 "
b101010 %
#650
1#
#700
b10 '
b10 +
b10 -
b101 !
b101 (
b101 )
b11 &
b11 *
b11 /
b1100 ,
b1011 .
0#
b111 $
b10111100 "
b10111100 %
#750
1#
#800
b11 '
b11 +
b11 -
b101 !
b101 (
b101 )
b10 &
b10 *
b10 /
b1011 ,
b101 .
0#
b1000 $
b1011011 "
b1011011 %
#850
1#
#900
b11 '
b11 +
b11 -
b100 !
b100 (
b100 )
b1 &
b1 *
b1 /
b111 ,
b1000 .
0#
b1001 $
b10000111 "
b10000111 %
#950
1#
#1000
b0 '
b0 +
b0 -
b11 !
b11 (
b11 )
b11 &
b11 *
b11 /
b0 ,
b1110 .
0#
b1010 $
b11100000 "
b11100000 %
