week2/ckt.v
module ckt (A2,B2,C2,D,Z);

    output D,Z;
    input A2, B2, C2;
    wire w1,w2;
    and G1 (w1, C2, B2);
    or G2 (D, w1, A2);
    and G3(w2,A2,B2);
    or G4(Z,D,w2);


endmodule

week2/tb_ckt.v

module tb_ckt;
    wire D, Z;
    reg A2, B2, C2;
    
    ckt M1 (A2, B2, C2, D, Z);
    initial begin
        A2 = 1'b0;
        B2 = 1'b0;
        C2 = 1'b0;

        #20 A2 = 1'b0;
        B2 = 1'b0;
        C2 = 1'b1;

        #20 A2 = 1'b0;
        B2 = 1'b1;
        C2 = 1'b0;

        #20 A2 = 1'b0;
        B2 = 1'b1;
        C2 = 1'b1;

        #20 A2 = 1'b1;
        B2 = 1'b0;
        C2 = 1'b0;

        #20 A2 = 1'b1;
        B2 = 1'b0;
        C2 = 1'b1;

        #20 A2 = 1'b1;
        B2 = 1'b1;
        C2 = 1'b0;

        #20 A2 = 1'b1;
        B2 = 1'b1;
        C2 = 1'b1;
    end
    initial begin
        $monitor($time, "  A2 = %b, B2 = %b, C2 = %b, D = %b, Z=%b", A2, B2, C2, D, Z);
    end
    initial begin
        $dumpfile("ckt.vcd");
        $dumpvars(0, tb_ckt);
    end
    initial begin
        #200
        $finish;

    end
endmodule

week2/ckt.vcd
$date
	Fri Aug 16 12:41:15 2024
$end
$version
	Icarus Verilog
$end
$timescale
	1s
$end
$scope module tb_ckt $end
$var wire 1 ! Z $end
$var wire 1 " D $end
$var reg 1 # A2 $end
$var reg 1 $ B2 $end
$var reg 1 % C2 $end
$scope module M1 $end
$var wire 1 # A2 $end
$var wire 1 $ B2 $end
$var wire 1 % C2 $end
$var wire 1 " D $end
$var wire 1 ! Z $end
$var wire 1 & w1 $end
$var wire 1 ' w2 $end
$upscope $end
$upscope $end
$enddefinitions $end
$comment Show the parameter values. $end
$dumpall
$end
#0
$dumpvars
0'
0&
0%
0$
0#
0"
0!
$end
#20
1%
#40
0%
1$
#60
1!
1"
1&
1%
#80
0&
0%
0$
1#
#100
1%
#120
1'
0%
1$
#140
1&
1%
