week3/muxx.v
module mux2(input wire i0, i1, j, output wire o);
    assign o = (j == 0) ? i0 : i1;
endmodule

module mux4(input wire [3:0] i, input wire j1, j0, output wire o);
    wire t0, t1;
    
    mux2 mux2_0(.i0(i[0]), .i1(i[1]), .j(j0), .o(t0));
    mux2 mux2_1(.i0(i[2]), .i1(i[3]), .j(j0), .o(t1));
    mux2 mux2_2(.i0(t0), .i1(t1), .j(j1), .o(o));
endmodule

*/

module invert(input wire i, output wire o);
assign o=!i;
endmodule
module and2(input wire i0, i1, output wire o);
assign o=i0 & i1;
endmodule
module or2(input wire i0, i1, output wire o);
assign o= i0|i1;
endmodule
module xor2(input wire i0, i1, output wire o);
assign o=i0^i1;
endmodule
module nand2(input wire i0, i1, output wire o);
wire t;
and2 and2_0(i0,i1,t);
invert invert_0(t, o);
endmodule
module nor2(input wire i0, i1, output wire o);
wire t;
or2 or2_0(i0,i1,t);
invert invert_0(t, o);
endmodule
module xnor2(input wire i0, i1, output wire o);
wire t;
xor2 xor2_0(i0,i1,t);
invert invert_0(t, o);
endmodule
module and3(input wire i0, i1,i2 output wire o);
wire t;
and2 and2_0(i0,i1,t);
and2 and2_0(i2,t,o);
endmodule
module or3(input wire i0, i1,i2 output wire o);
wire t;
or2 or2_0(i0,i1,t);
or2 or2_1(i2,t,o);
endmodule
module nor3(input wire i0, i1,i2 output wire o);
wire t;
or2 or2_0(i0,i1,t);
nor2 nor2_0(i2,t,o);
endmodule
module nand3(input wire i0, i1,i2 output wire o);
wire t;
and2 and2_0(i0,i1,t);
and2 and2_0(i2,t,o);
endmodule
module xor3(input wire i0, i1,i2 output wire o);
wire t;
xor2 xor2_0(i0,i1,t);
xor2 xor2_1(i2,t,o);
endmodule



module fa (input wire i0, i1,cin, output wire sum ,count)
wire t0, t1, t2;
xor3 _i0(i0,i1,cin,sum);
and2 _i1(i0,i1,t0);
and2 _i2
endmodule

week3/muxx_tb.v

module test;
    reg [3:0] ii;
    reg s0, s1;
    wire yy;

    initial begin
        $dumpfile("test.vcd");
        $dumpvars(0, test);
    end

    mux4 newMux(.i(ii), .j0(s0), .j1(s1), .o(yy));

    initial begin
      $monitor("ii=%b; s0=%b; s1=%b, output=%b", ii, s0, s1, yy);
        ii = 4'b0000; s0 = 1'b0; s1 = 1'b0;
        #5 ii = 4'b1000; s0 = 1'b0; s1 = 1'b0;
        #5 ii = 4'b0000; s0 = 1'b0; s1 = 1'b1;
        #5 ii = 4'b0100; s0 = 1'b0; s1 = 1'b0;
        #5 ii = 4'b0000; s0 = 1'b1; s1 = 1'b1;
        #5 ii = 4'b0010; s0 = 1'b1; s1 = 1'b0;
        #5 ii = 4'b0000; s0 = 1'b1; s1 = 1'b1;
        #5 ii = 4'b0001; s0 = 1'b1; s1 = 1'b0;
       
    end
endmodule

week3/test.vcd
$date
	Fri Aug 30 12:08:20 2024
$end
$version
	Icarus Verilog
$end
$timescale
	1s
$end
$scope module test $end
$var wire 1 ! yy $end
$var reg 4 " ii [3:0] $end
$var reg 1 # s0 $end
$var reg 1 $ s1 $end
$scope module newMux $end
$var wire 4 % i [3:0] $end
$var wire 1 # j0 $end
$var wire 1 $ j1 $end
$var wire 1 & t1 $end
$var wire 1 ' t0 $end
$var wire 1 ! o $end
$scope module mux2_0 $end
$var wire 1 ( i0 $end
$var wire 1 ) i1 $end
$var wire 1 # j $end
$var wire 1 ' o $end
$upscope $end
$scope module mux2_1 $end
$var wire 1 * i0 $end
$var wire 1 + i1 $end
$var wire 1 # j $end
$var wire 1 & o $end
$upscope $end
$scope module mux2_2 $end
$var wire 1 ' i0 $end
$var wire 1 & i1 $end
$var wire 1 $ j $end
$var wire 1 ! o $end
$upscope $end
$upscope $end
$upscope $end
$enddefinitions $end
$comment Show the parameter values. $end
$dumpall
$end
#0
$dumpvars
0+
0*
0)
0(
0'
0&
b0 %
0$
0#
b0 "
0!
$end
#5
1+
b1000 "
b1000 %
#10
0+
1$
b0 "
b0 %
#15
1&
1*
0$
b100 "
b100 %
#20
0&
0*
1$
1#
b0 "
b0 %
#25
1!
1'
1)
0$
b10 "
b10 %
#30
0!
0'
0)
1$
b0 "
b0 %
#35
1(
0$
b1 "
b1 %
